remote_web_typing/__init__.py
remote_web_typing/main.py
remote_web_typing-0.1.4.dist-info/WHEEL
remote_web_typing-0.1.4.dist-info/entry_points.txt
remote_web_typing-0.1.4.dist-info/METADATA
remote_web_typing-0.1.4.dist-info/RECORD
