Metadata-Version: 2.3
Name: remote-web-typing
Version: 0.1.4
Summary: Remote Web Typing is a Python web application that lets you type on your computer from another device (like a phone) on the same network.
Author: mayank
Author-email: mayank <mayankchodharysept17@gmail.com>
Requires-Dist: flask>=3.1.2
Requires-Dist: keyboard>=0.13.5
Requires-Dist: pillow>=11.3.0
Requires-Dist: pyautogui>=0.9.54
Requires-Dist: pyperclip>=1.9.0
Requires-Python: >=3.12
Project-URL: Homepage, https://github.com/Mayank170906/remote-web-typing
Project-URL: Issues, https://github.com/Mayank170906/remote-web-typing/issues
